sweet_notebook_components/__init__.py
sweet_notebook_components/component.py
sweet_notebook_components/renderer.py
sweet_notebook_components/serializer.py
sweet_notebook_components/st.py
tests/__init__.py
tests/test_serializer.py
tests/test_text.py
sweet_notebook_components-1.0.5.dist-info/LICENSE
sweet_notebook_components-1.0.5.dist-info/METADATA
sweet_notebook_components-1.0.5.dist-info/WHEEL
sweet_notebook_components-1.0.5.dist-info/top_level.txt
sweet_notebook_components-1.0.5.dist-info/RECORD
