Metadata-Version: 2.1
Name: sweet-notebook-components
Version: 1.0.5
Summary: A Streamlit-like component library for Notebooks.
Home-page: https://github.com/artmann/sweet_components
Author: Christoffer Artmann
Author-email: Artgaard@gmail.com
License: UNKNOWN
Platform: UNKNOWN
Classifier: Programming Language :: Python :: 3
Classifier: License :: OSI Approved :: MIT License
Classifier: Operating System :: OS Independent
Requires-Python: >=3.6
License-File: LICENSE
Requires-Dist: IPython
